{
  "platform": "instagram",
  "platform_name": "Instagram",
  "description": "写真・動画中心のSNS。キラキラ起業女子、丁寧な暮らし演出、匂わせ、DM誘導など独自のテンプレ文化が発達。ビジュアル重視ゆえにキャプションが定型化しやすく、承認欲求・ビジネス臭が凝縮される場となっている。",
  "categories": [
    {
      "id": "kigyou_joshi",
      "name": "起業女子構文",
      "description": "「好きを仕事に」「自分らしく生きる」を旗印に、実態は高額講座への集客導線。2010年代はアメブロ、2020年以降はInstagramに主戦場が移行。月1万円以上稼げているのは上位20%程度とされる。",
      "phrases": [
        {
          "text": "好きを仕事に",
          "position": "opening",
          "reality": "「好き」の定義が曖昧なまま使われるマジックワード。実態は「集客を仕事に」",
          "example": "好きを仕事にして3年。あの頃の私に「大丈夫だよ」って伝えたい",
          "intensity": 5,
          "tags": [
            "起業女子",
            "自己実現風"
          ]
        },
        {
          "text": "自分らしく生きる",
          "position": "closing",
          "reality": "「自分らしさ」の中身が「会社を辞めること」に矮小化されがち",
          "example": "誰かの正解じゃなくて、自分らしく生きる道を選んだ",
          "intensity": 4,
          "tags": [
            "起業女子",
            "脱サラ美化"
          ]
        },
        {
          "text": "会社員時代の私へ",
          "position": "opening",
          "reality": "会社員を「不幸な過去」として利用するマウント構文",
          "example": "会社員時代の私へ。大丈夫、1年後には月商100万超えてるよ",
          "intensity": 5,
          "tags": [
            "起業女子",
            "ビフォーアフター"
          ]
        },
        {
          "text": "起業して○年",
          "position": "opening",
          "reality": "年数を権威づけに使うが、売上の内訳は不透明",
          "example": "起業して3年。たくさんの出会いと学びに感謝しかない",
          "intensity": 3,
          "tags": [
            "起業女子",
            "実績アピール"
          ]
        },
        {
          "text": "私にもできたんだから、あなたにもできる",
          "position": "closing",
          "reality": "再現性の根拠ゼロ。高額講座への導線",
          "example": "何のスキルもなかった私にもできたんだから、あなたにもできる。一緒に変わろう",
          "intensity": 5,
          "tags": [
            "起業女子",
            "勧誘"
          ]
        },
        {
          "text": "お客様の声をいただきました",
          "position": "opening",
          "reality": "自作自演や仲間内の相互レビューの可能性大",
          "example": "嬉しいお客様の声をいただきました！「人生が変わりました」って最高の褒め言葉",
          "intensity": 4,
          "tags": [
            "起業女子",
            "社会的証明"
          ]
        },
        {
          "text": "満席→増席→残席わずか",
          "position": "middle",
          "reality": "希少性の演出。本当に満席かは不明",
          "example": "大好評につき満席→2席増席しました！残席わずかです",
          "intensity": 5,
          "tags": [
            "起業女子",
            "煽り"
          ]
        },
        {
          "text": "世界観を整える",
          "position": "middle",
          "reality": "中身より見た目の統一感を重視する本末転倒",
          "example": "インスタの世界観を整えたら、理想のお客様が集まるようになった",
          "intensity": 3,
          "tags": [
            "起業女子",
            "SNSブランディング"
          ]
        }
      ]
    },
    {
      "id": "kirakira",
      "name": "キラキラ構文",
      "description": "「感謝」「最高」「幸せ」を多用し、充実した毎日を演出する構文群。キラキラ起業女子の基本装備であり、ランチ会・お茶会の集合写真と共に投稿される。実態は「承認欲求を満たすビジネス」。",
      "phrases": [
        {
          "text": "今日も感謝",
          "position": "closing",
          "reality": "感謝の安売り。何に感謝しているか具体性がない",
          "example": "素敵なカフェで打ち合わせ。最高の仲間に恵まれて今日も感謝",
          "intensity": 4,
          "tags": [
            "キラキラ",
            "感謝演出"
          ]
        },
        {
          "text": "最高の仲間",
          "position": "middle",
          "reality": "同じ高額講座の受講生仲間。利害関係で繋がっている",
          "example": "最高の仲間と最高の時間。この出会いに感謝しかない",
          "intensity": 5,
          "tags": [
            "キラキラ",
            "仲間アピール"
          ]
        },
        {
          "text": "感謝しかない",
          "position": "closing",
          "reality": "「しかない」と言い切ることで思考停止を演出",
          "example": "今年も素敵な1年でした。関わってくれた全ての人に感謝しかない",
          "intensity": 5,
          "tags": [
            "キラキラ",
            "感謝演出"
          ]
        },
        {
          "text": "人生変わった",
          "position": "middle",
          "reality": "変わったのは「投稿内容」だけの可能性",
          "example": "あのセミナーに参加して人生変わった。行動した自分を褒めたい",
          "intensity": 5,
          "tags": [
            "キラキラ",
            "変容アピール"
          ]
        },
        {
          "text": "幸せすぎる",
          "position": "closing",
          "reality": "「すぎる」の多用は語彙力の枯渇",
          "example": "大好きな仕事ができて幸せすぎる毎日",
          "intensity": 4,
          "tags": [
            "キラキラ",
            "幸福アピール"
          ]
        },
        {
          "text": "夢が叶った",
          "position": "opening",
          "reality": "夢のハードルが異常に低い場合が多い",
          "example": "夢が叶った！ずっとやりたかったセミナー開催できました",
          "intensity": 4,
          "tags": [
            "キラキラ",
            "達成アピール"
          ]
        },
        {
          "text": "ご縁に感謝",
          "position": "closing",
          "reality": "ビジネス上の取引を「ご縁」でスピリチュアル化",
          "example": "素敵なコラボが実現！ご縁に感謝です",
          "intensity": 4,
          "tags": [
            "キラキラ",
            "スピ系"
          ]
        },
        {
          "text": "愛しかない",
          "position": "closing",
          "reality": "「感謝しかない」の亜種。具体性ゼロ",
          "example": "この仲間たちへの愛しかない。ほんとに大好き",
          "intensity": 4,
          "tags": [
            "キラキラ",
            "愛演出"
          ]
        },
        {
          "text": "毎日がご褒美",
          "position": "closing",
          "reality": "毎日ご褒美なら、それはもう「日常」",
          "example": "好きなことして生きてるから毎日がご褒美",
          "intensity": 4,
          "tags": [
            "キラキラ",
            "幸福アピール"
          ]
        }
      ]
    },
    {
      "id": "before_after",
      "name": "ビフォーアフター構文",
      "description": "過去の不幸な自分と現在のキラキラした自分を対比させる構文。ダイエット系と起業系で多用される。ビフォー写真は意図的に暗く撮り、アフター写真は加工盛り盛りというテクニックが定番。",
      "phrases": [
        {
          "text": "○ヶ月前の私に教えてあげたい",
          "position": "opening",
          "reality": "数ヶ月で人生が変わる程度の悩みだったのでは",
          "example": "3ヶ月前の私に教えてあげたい。大丈夫、未来は明るいよ",
          "intensity": 4,
          "tags": [
            "ビフォーアフター",
            "過去の自分語り"
          ]
        },
        {
          "text": "あの頃の自分には想像もできなかった",
          "position": "middle",
          "reality": "想像できなかったのは、こんな痛い投稿をする自分の姿では",
          "example": "会社員だったあの頃の自分には想像もできなかった景色",
          "intensity": 4,
          "tags": [
            "ビフォーアフター",
            "変容アピール"
          ]
        },
        {
          "text": "○kg痩せました",
          "position": "opening",
          "reality": "ビフォー写真の姿勢・照明・服装で盛大にサバを読んでいる",
          "example": "3ヶ月で-10kg痩せました！左がBefore、右がAfter",
          "intensity": 3,
          "tags": [
            "ビフォーアフター",
            "ダイエット"
          ]
        },
        {
          "text": "過去の自分を超えていく",
          "position": "closing",
          "reality": "比較対象が自分だけなので永遠に「成長」できる魔法の言葉",
          "example": "毎日少しずつでいい。過去の自分を超えていく",
          "intensity": 3,
          "tags": [
            "ビフォーアフター",
            "自己啓発"
          ]
        },
        {
          "text": "あの時、一歩踏み出してよかった",
          "position": "closing",
          "reality": "「一歩踏み出す」＝高額講座に申し込んだだけ",
          "example": "あの時、勇気を出して一歩踏み出してよかった。今の自分が好き",
          "intensity": 4,
          "tags": [
            "ビフォーアフター",
            "起業女子"
          ]
        },
        {
          "text": "昔の私は○○だった",
          "position": "opening",
          "reality": "過去の自分を踏み台にするナルシシズム",
          "example": "昔の私は自信がなくて、人の目ばかり気にしてた。でも今は違う",
          "intensity": 4,
          "tags": [
            "ビフォーアフター",
            "自分語り"
          ]
        },
        {
          "text": "劇的ビフォーアフター",
          "position": "opening",
          "reality": "テレビ番組のパロディ。劇的なのは加工技術",
          "example": "【劇的ビフォーアフター】垢抜けって本当にすごい",
          "intensity": 3,
          "tags": [
            "ビフォーアフター",
            "美容"
          ]
        }
      ]
    },
    {
      "id": "cafe_teinei",
      "name": "カフェ・丁寧な暮らし構文",
      "description": "ハンドドリップコーヒー、花のある暮らし、手作り料理を「丁寧な暮らし」として発信する構文群。Instagramの#丁寧な暮らし は400万件超。承認欲求の表れ、余裕マウントとして批判されることも多い。",
      "phrases": [
        {
          "text": "丁寧な暮らし",
          "position": "middle",
          "reality": "撮影用に整えた空間。日常は散らかっている可能性大",
          "example": "休日はゆっくりハンドドリップ。丁寧な暮らしを心がけてます",
          "intensity": 4,
          "tags": [
            "丁寧な暮らし",
            "ライフスタイル"
          ]
        },
        {
          "text": "おうちカフェ",
          "position": "opening",
          "reality": "自宅でコーヒー淹れただけ。「カフェ」要素は食器のみ",
          "example": "おうちカフェでほっとひと息。今日はラテアート挑戦してみた",
          "intensity": 3,
          "tags": [
            "カフェ",
            "丁寧な暮らし"
          ]
        },
        {
          "text": "お気に入りの○○",
          "position": "opening",
          "reality": "「お気に入り」を連発するブランド紹介の隠れ蓑",
          "example": "お気に入りのマグカップでモーニング。この時間が一番好き",
          "intensity": 3,
          "tags": [
            "丁寧な暮らし",
            "物アピール"
          ]
        },
        {
          "text": "花のある暮らし",
          "position": "middle",
          "reality": "撮影のために買った花。枯れた後の投稿はない",
          "example": "今週のお花はチューリップ。花のある暮らしって心が整う",
          "intensity": 3,
          "tags": [
            "丁寧な暮らし",
            "インテリア"
          ]
        },
        {
          "text": "自分を整える時間",
          "position": "closing",
          "reality": "整えているのは撮影角度とフィルター",
          "example": "朝ヨガとハーブティーで自分を整える時間。これが私のルーティン",
          "intensity": 4,
          "tags": [
            "丁寧な暮らし",
            "セルフケア"
          ]
        },
        {
          "text": "何気ない日常が愛おしい",
          "position": "closing",
          "reality": "何気なくない。綿密に構図を計算している",
          "example": "窓から差し込む光とコーヒーの香り。何気ない日常が愛おしい",
          "intensity": 4,
          "tags": [
            "丁寧な暮らし",
            "ポエム"
          ]
        },
        {
          "text": "暮らしを楽しむ",
          "position": "closing",
          "reality": "「楽しむ」より「見せる」が主目的",
          "example": "季節の食材で作り置き。暮らしを楽しむって素敵なこと",
          "intensity": 3,
          "tags": [
            "丁寧な暮らし",
            "料理"
          ]
        },
        {
          "text": "ていねいに暮らす",
          "position": "middle",
          "reality": "ていねいなのは写真編集だけかもしれない",
          "example": "朝、丁寧にお味噌汁を作る。ていねいに暮らすって決めた2024年",
          "intensity": 3,
          "tags": [
            "丁寧な暮らし",
            "意識高い"
          ]
        }
      ]
    },
    {
      "id": "hashtag",
      "name": "ハッシュタグ構文",
      "description": "大量のハッシュタグを羅列し、リーチ拡大を狙う構文。2025年12月にInstagram公式が「最大5個まで」制限を発表。投稿と無関係なタグの乱用、ハッシュタグで文章を作る謎の文化も存在。",
      "phrases": [
        {
          "text": "#○○好きな人と繋がりたい",
          "position": "closing",
          "reality": "繋がりたいのではなくフォロワーが欲しいだけ",
          "example": "#カフェ好きな人と繋がりたい #写真好きな人と繋がりたい",
          "intensity": 4,
          "tags": [
            "ハッシュタグ",
            "フォロワー稼ぎ"
          ]
        },
        {
          "text": "#instagood #photooftheday",
          "position": "closing",
          "reality": "意味を理解せず付けている人多数。効果はほぼゼロ",
          "example": "#instagood #photooftheday #instadaily #instalike #beautiful",
          "intensity": 3,
          "tags": [
            "ハッシュタグ",
            "英語タグ乱用"
          ]
        },
        {
          "text": "#○○な人と繋がれ",
          "position": "closing",
          "reality": "命令形タグ。繋がれと言われても",
          "example": "#起業女子と繋がれ #ママ起業家と繋がれ",
          "intensity": 4,
          "tags": [
            "ハッシュタグ",
            "起業女子"
          ]
        },
        {
          "text": "#今日のコーデ #ootd",
          "position": "closing",
          "reality": "毎日投稿するほどのコーデかは疑問",
          "example": "#今日のコーデ #ootd #コーデ記録 #プチプラコーデ #着回しコーデ",
          "intensity": 2,
          "tags": [
            "ハッシュタグ",
            "ファッション"
          ]
        },
        {
          "text": "ハッシュタグで文章を作る",
          "position": "closing",
          "reality": "ハッシュタグの機能を完全に誤解している",
          "example": "#今日 は #東京 に #旅行 に来てます #楽しい",
          "intensity": 3,
          "tags": [
            "ハッシュタグ",
            "誤用"
          ]
        },
        {
          "text": "30個タグ羅列",
          "position": "closing",
          "reality": "数打ちゃ当たる精神。内容と無関係なタグが半数以上",
          "example": "#カフェ #カフェ巡り #カフェスタグラム #東京カフェ #カフェ好き #おしゃれカフェ #隠れ家カフェ...(以下20個)",
          "intensity": 5,
          "tags": [
            "ハッシュタグ",
            "スパム"
          ]
        },
        {
          "text": "#○○部",
          "position": "closing",
          "reality": "勝手に部活を作る文化。部員はタグを付けた全員",
          "example": "#おうちごはん部 #カフェ部 #筋トレ部 #朝活部",
          "intensity": 2,
          "tags": [
            "ハッシュタグ",
            "コミュニティごっこ"
          ]
        }
      ]
    },
    {
      "id": "stories",
      "name": "ストーリーズ構文",
      "description": "24時間で消えるストーリーズ特有の構文。質問箱の自作自演、匂わせ投稿、意味深ポエムが三大要素。消えるからこそ攻めた内容を投稿できるという心理が働く。",
      "phrases": [
        {
          "text": "質問ある？",
          "position": "opening",
          "reality": "聞かれてもいないのに自分から質問を募集する承認欲求",
          "example": "暇だから質問ある？なんでも答えるよ！",
          "intensity": 4,
          "tags": [
            "ストーリーズ",
            "質問箱"
          ]
        },
        {
          "text": "これ知ってた？",
          "position": "opening",
          "reality": "知ってた情報を「特別な知識」として発信するマウント",
          "example": "これ知ってた？実は○○って△△なんだよ！",
          "intensity": 3,
          "tags": [
            "ストーリーズ",
            "豆知識マウント"
          ]
        },
        {
          "text": "匂わせ2人分の食事",
          "position": "middle",
          "reality": "彼氏がいることを直接言わず写真で察させる最頻出テクニック",
          "example": "(2人分のカフェラテの写真) 「幸せな時間」",
          "intensity": 4,
          "tags": [
            "ストーリーズ",
            "匂わせ"
          ]
        },
        {
          "text": "意味深ポエム",
          "position": "middle",
          "reality": "誰に向けたメッセージか分からない独り言。構ってほしいだけ",
          "example": "分かってくれる人にだけ伝わればいい。",
          "intensity": 4,
          "tags": [
            "ストーリーズ",
            "メンヘラ"
          ]
        },
        {
          "text": "今日のご褒美",
          "position": "opening",
          "reality": "毎日ご褒美を買っているのでもはやご褒美ではない",
          "example": "頑張った自分に今日のご褒美 (高級スイーツの写真)",
          "intensity": 3,
          "tags": [
            "ストーリーズ",
            "自分へのご褒美"
          ]
        },
        {
          "text": "これめっちゃよかった！",
          "position": "opening",
          "reality": "PR案件の可能性。「めっちゃ」の安売り",
          "example": "これめっちゃよかった！リピ確定 (コスメの写真)",
          "intensity": 3,
          "tags": [
            "ストーリーズ",
            "レビュー風PR"
          ]
        },
        {
          "text": "○○な人は挙手して",
          "position": "opening",
          "reality": "エンゲージメント稼ぎ。アルゴリズムハック",
          "example": "朝活してる人は挙手して！",
          "intensity": 3,
          "tags": [
            "ストーリーズ",
            "参加型"
          ]
        }
      ]
    },
    {
      "id": "reels",
      "name": "リール構文",
      "description": "短尺動画リールのキャプションやテロップで使われる構文。「保存推奨」「最後まで見て」でアルゴリズムをハックし、視聴完了率と保存数を稼ぐことが最優先。内容の質は二の次。",
      "phrases": [
        {
          "text": "保存推奨",
          "position": "opening",
          "reality": "保存するほどの価値があるかは視聴者が決めること",
          "example": "【保存推奨】知らないと損する○○の裏ワザ",
          "intensity": 4,
          "tags": [
            "リール",
            "アルゴリズムハック"
          ]
        },
        {
          "text": "最後まで見て",
          "position": "opening",
          "reality": "視聴完了率を稼ぐための煽り。最後にオチがない場合も多い",
          "example": "最後まで見て！衝撃の結末が...",
          "intensity": 4,
          "tags": [
            "リール",
            "視聴維持"
          ]
        },
        {
          "text": "知らないと損する",
          "position": "opening",
          "reality": "知らなくても損しない情報がほとんど",
          "example": "【知らないと損する】○○の意外な使い方5選",
          "intensity": 4,
          "tags": [
            "リール",
            "煽りタイトル"
          ]
        },
        {
          "text": "○○選",
          "position": "opening",
          "reality": "リスト形式にすれば何でもコンテンツになるという安易さ",
          "example": "買ってよかったもの5選 / やめてよかったこと3選",
          "intensity": 3,
          "tags": [
            "リール",
            "リスト構文"
          ]
        },
        {
          "text": "○○してる人だけいいねして",
          "position": "closing",
          "reality": "エンゲージメント乞食。いいねの基準が曖昧",
          "example": "朝活してる人だけいいねして！",
          "intensity": 4,
          "tags": [
            "リール",
            "エンゲージメント乞食"
          ]
        },
        {
          "text": "まだ知らないの？",
          "position": "opening",
          "reality": "上から目線で視聴者を煽るマウント型導入",
          "example": "え、まだ知らないの？○○の裏ワザ",
          "intensity": 4,
          "tags": [
            "リール",
            "マウント導入"
          ]
        },
        {
          "text": "フォローしないと損",
          "position": "closing",
          "reality": "フォローしなくても何も損しない",
          "example": "こういう情報を毎日発信中！フォローしないと損だよ",
          "intensity": 5,
          "tags": [
            "リール",
            "フォロー煽り"
          ]
        },
        {
          "text": "正直教えたくない",
          "position": "opening",
          "reality": "教えたくないなら投稿しなければいい。矛盾の塊",
          "example": "正直教えたくない...穴場カフェ3選",
          "intensity": 4,
          "tags": [
            "リール",
            "秘密演出"
          ]
        }
      ]
    },
    {
      "id": "dm_yudou",
      "name": "DM誘導構文",
      "description": "投稿やストーリーからDMに誘導し、クローズドな場でセールスを行う構文。「詳しくはDMで」は情報商材系の常套句。コメントで特定ワードを送らせてDM自動送信するアルゴリズムハック手法も急増。",
      "phrases": [
        {
          "text": "詳しくはDMで",
          "position": "closing",
          "reality": "公開の場で言えない=怪しい内容の証拠",
          "example": "気になる方は詳しくはDMでお伝えします！",
          "intensity": 5,
          "tags": [
            "DM誘導",
            "情報商材"
          ]
        },
        {
          "text": "○○と送ってね",
          "position": "closing",
          "reality": "自動DM送信ツールへの導線。送信数でアルゴリズムをハック",
          "example": "知りたい人はDMに「テンプレ」と送ってね！",
          "intensity": 5,
          "tags": [
            "DM誘導",
            "自動化"
          ]
        },
        {
          "text": "コメントで○○と書いてね",
          "position": "closing",
          "reality": "コメント数を水増しし、投稿のリーチを伸ばす戦術",
          "example": "欲しい人はコメントで「プレゼント」と書いてね！",
          "intensity": 5,
          "tags": [
            "DM誘導",
            "コメント誘導"
          ]
        },
        {
          "text": "無料プレゼント",
          "position": "opening",
          "reality": "無料の裏に高額商品の販売導線が必ずある",
          "example": "【無料プレゼント】SNS集客テンプレートを限定配布中！",
          "intensity": 5,
          "tags": [
            "DM誘導",
            "フリーミアム"
          ]
        },
        {
          "text": "気になる方はプロフィールのリンクから",
          "position": "closing",
          "reality": "リンク先はLINE公式アカウント→ステップ配信→高額講座",
          "example": "もっと知りたい方はプロフィールのリンクから！",
          "intensity": 4,
          "tags": [
            "DM誘導",
            "導線設計"
          ]
        },
        {
          "text": "LINE登録で○○プレゼント",
          "position": "closing",
          "reality": "LINE登録＝見込み客リスト入り。プレゼントは安価なPDF",
          "example": "LINE登録で「月収100万テンプレ」プレゼント中！",
          "intensity": 5,
          "tags": [
            "DM誘導",
            "LINE誘導"
          ]
        },
        {
          "text": "限定○名",
          "position": "middle",
          "reality": "限定と言いつつ常に募集している。希少性の演出",
          "example": "今月限定3名だけ個別相談受付中！",
          "intensity": 5,
          "tags": [
            "DM誘導",
            "限定煽り"
          ]
        }
      ]
    },
    {
      "id": "jikokeihatu",
      "name": "自己啓発構文",
      "description": "「マインドセット」「成功者の習慣」「行動が全て」など、自己啓発書の受け売りを投稿する構文群。誰でも言える一般論を「気づき」として発信。「成功者の法則」系は投稿者自身が成功していない矛盾。",
      "phrases": [
        {
          "text": "行動した人だけが変われる",
          "position": "closing",
          "reality": "「行動」＝自分の講座に申し込むこと",
          "example": "迷ってる時間がもったいない。行動した人だけが変われる",
          "intensity": 4,
          "tags": [
            "自己啓発",
            "行動論"
          ]
        },
        {
          "text": "マインドセットが全て",
          "position": "opening",
          "reality": "具体的なスキルや知識を教えられない人の逃げ口上",
          "example": "成功できない原因はスキルじゃない。マインドセットが全て",
          "intensity": 5,
          "tags": [
            "自己啓発",
            "マインドセット"
          ]
        },
        {
          "text": "成功者の○○",
          "position": "opening",
          "reality": "「成功者」の定義が不明。発信者自身は成功者なのか",
          "example": "成功者の朝のルーティン5選。あなたはいくつやってる？",
          "intensity": 4,
          "tags": [
            "自己啓発",
            "成功者語り"
          ]
        },
        {
          "text": "環境を変えれば人は変わる",
          "position": "middle",
          "reality": "「環境を変える」＝自分のコミュニティに入れという意味",
          "example": "人は環境の生き物。環境を変えれば人は変わる",
          "intensity": 4,
          "tags": [
            "自己啓発",
            "環境論"
          ]
        },
        {
          "text": "やらない理由を探すな",
          "position": "closing",
          "reality": "やらない理由を冷静に分析することこそ重要",
          "example": "できない理由じゃなくて、できる方法を考えよう。やらない理由を探すな",
          "intensity": 4,
          "tags": [
            "自己啓発",
            "根性論"
          ]
        },
        {
          "text": "人生は一度きり",
          "position": "opening",
          "reality": "当たり前すぎる事実をドヤ顔で言う",
          "example": "人生は一度きり。やりたいことをやろう",
          "intensity": 3,
          "tags": [
            "自己啓発",
            "名言風"
          ]
        },
        {
          "text": "自分に投資する",
          "position": "middle",
          "reality": "「投資」と言い換えることで高額出費を正当化させる話術",
          "example": "自分に投資することをケチらない。それが未来を変える",
          "intensity": 5,
          "tags": [
            "自己啓発",
            "高額講座誘導"
          ]
        },
        {
          "text": "本気で変わりたい人だけ",
          "position": "opening",
          "reality": "参加しない人を「本気じゃない人」と暗にディスる",
          "example": "本気で変わりたい人だけ見てください",
          "intensity": 4,
          "tags": [
            "自己啓発",
            "選民意識"
          ]
        }
      ]
    },
    {
      "id": "mount",
      "name": "マウント・匂わせ構文",
      "description": "高級品、旅行、ハイスペ彼氏の存在をさりげなく見せつける構文。「さりげない」つもりが全くさりげなくない。匂わせ投稿1位は「カフェでの相手の食事写り込み」(42.8%)。",
      "phrases": [
        {
          "text": "見切れブランドロゴ",
          "position": "middle",
          "reality": "偶然映り込んだ風を装った計算された構図",
          "example": "(背景にエルメスの紙袋が見切れた自撮り) 「今日も1日お疲れ様」",
          "intensity": 5,
          "tags": [
            "マウント",
            "ブランド匂わせ"
          ]
        },
        {
          "text": "ありがとう(彼氏向け)",
          "position": "closing",
          "reality": "フォロワーに見せつけるための、彼氏への公開感謝",
          "example": "(プレゼントの写真) 「ありがとう。嬉しかった」",
          "intensity": 4,
          "tags": [
            "マウント",
            "匂わせ"
          ]
        },
        {
          "text": "連れてきてもらった",
          "position": "opening",
          "reality": "「連れてきてもらった」＝彼氏がいて、しかも奢りという二重マウント",
          "example": "素敵なお店に連れてきてもらった。幸せ",
          "intensity": 4,
          "tags": [
            "マウント",
            "匂わせ"
          ]
        },
        {
          "text": "○回目の訪問",
          "position": "opening",
          "reality": "高級店のリピーターアピール＝経済力マウント",
          "example": "ここは3回目の訪問。何度来ても最高",
          "intensity": 3,
          "tags": [
            "マウント",
            "リピートアピール"
          ]
        },
        {
          "text": "自分へのご褒美",
          "position": "opening",
          "reality": "高級品の購入を「ご褒美」で正当化。頻度が高すぎ",
          "example": "頑張った自分へのご褒美。ずっと欲しかったバッグ",
          "intensity": 4,
          "tags": [
            "マウント",
            "購入正当化"
          ]
        },
        {
          "text": "2人分の食器・飲み物",
          "position": "middle",
          "reality": "匂わせテクニック第1位。わざと2人分を写す",
          "example": "(2人分のカプチーノの写真) 「至福のひととき」",
          "intensity": 4,
          "tags": [
            "マウント",
            "匂わせ"
          ]
        },
        {
          "text": "これで○○円は安い",
          "position": "middle",
          "reality": "値段を出すこと自体が経済力マウント",
          "example": "このコースでこのクオリティで8000円は安い！",
          "intensity": 3,
          "tags": [
            "マウント",
            "値段マウント"
          ]
        },
        {
          "text": "男性の手や物の映り込み",
          "position": "middle",
          "reality": "彼氏の存在を「偶然」映り込ませる高等テクニック",
          "example": "(ネイルの写真に男性の腕時計が映り込み) 「ネイル変えた！」",
          "intensity": 5,
          "tags": [
            "マウント",
            "匂わせ"
          ]
        }
      ]
    },
    {
      "id": "profile",
      "name": "プロフィール構文",
      "description": "150文字の自己紹介欄に凝縮される自己ブランディング構文。「○歳で脱サラ」「月商○万」「元○○」の肩書き盛りが定番。3行目以降は「続きを読む」に隠れるため、冒頭に最も強い訴求を持ってくる。",
      "phrases": [
        {
          "text": "○歳で脱サラ",
          "position": "opening",
          "reality": "年齢と「脱サラ」の組み合わせで行動力をアピール。退職理由は不問",
          "example": "28歳で脱サラ｜好きを仕事に月商100万",
          "intensity": 5,
          "tags": [
            "プロフィール",
            "肩書き盛り"
          ]
        },
        {
          "text": "月商○万",
          "position": "opening",
          "reality": "「月商」であって「月収」ではない。経費を引くと赤字の可能性も",
          "example": "元OL→起業3年で月商300万｜SNS集客のプロ",
          "intensity": 5,
          "tags": [
            "プロフィール",
            "数字マウント"
          ]
        },
        {
          "text": "元○○→現○○",
          "position": "opening",
          "reality": "ビフォーアフターのプロフィール版。落差が大きいほど効果的",
          "example": "元うつ病会社員→フリーランスで年収1000万",
          "intensity": 5,
          "tags": [
            "プロフィール",
            "変容ストーリー"
          ]
        },
        {
          "text": "○○のプロ / ○○の専門家",
          "position": "opening",
          "reality": "自称「プロ」「専門家」。資格や実績の裏付けがない場合が多い",
          "example": "SNS集客のプロ｜3000人以上をサポート",
          "intensity": 4,
          "tags": [
            "プロフィール",
            "自称専門家"
          ]
        },
        {
          "text": "○○を発信中",
          "position": "closing",
          "reality": "フォローする理由を提示するCTA。内容は薄い場合も",
          "example": "30代ママの時短レシピを毎日発信中！",
          "intensity": 2,
          "tags": [
            "プロフィール",
            "CTA"
          ]
        },
        {
          "text": "フォローで○○が手に入る",
          "position": "closing",
          "reality": "フォローするだけで人生が変わるわけがない",
          "example": "フォローするだけで痩せるマインドが手に入る",
          "intensity": 4,
          "tags": [
            "プロフィール",
            "誇大表現"
          ]
        },
        {
          "text": "○○ママ / ○児の母",
          "position": "opening",
          "reality": "母親属性で親近感を演出しつつビジネス誘導",
          "example": "2児のママ｜育児しながら在宅で月50万",
          "intensity": 3,
          "tags": [
            "プロフィール",
            "ママ起業"
          ]
        },
        {
          "text": "リンクまとめはこちら→",
          "position": "closing",
          "reality": "lit.linkやlinktreeへの誘導。その先に複数の導線が待ち構える",
          "example": "全てのリンクはこちら→ lit.link/xxxxx",
          "intensity": 2,
          "tags": [
            "プロフィール",
            "リンク誘導"
          ]
        }
      ]
    },
    {
      "id": "collab_pr",
      "name": "コラボ・PR構文",
      "description": "企業からの提供品やPR案件を紹介する構文。2023年10月のステマ規制以降「#PR」「#広告」の表記が義務化。しかし「本当に気に入ったものだけ紹介してます」と前置きしつつ、毎日PR投稿する矛盾。",
      "phrases": [
        {
          "text": "○○様からご提供いただきました",
          "position": "opening",
          "reality": "提供品＝無料。無料でもらった物を絶賛するのは当然",
          "example": "○○様からご提供いただきました！使ってみたら本当によかった",
          "intensity": 3,
          "tags": [
            "PR",
            "提供"
          ]
        },
        {
          "text": "本当に気に入ったものだけ紹介してます",
          "position": "opening",
          "reality": "この前置きがある時点でステマ疑惑への予防線",
          "example": "本当に気に入ったものだけ紹介してます。今回の○○は控えめに言って最高",
          "intensity": 4,
          "tags": [
            "PR",
            "信頼性演出"
          ]
        },
        {
          "text": "控えめに言って最高",
          "position": "middle",
          "reality": "「控えめ」と言いながら全力で推している矛盾",
          "example": "これ控えめに言って最高すぎる...！リピ確定",
          "intensity": 4,
          "tags": [
            "PR",
            "過剰表現"
          ]
        },
        {
          "text": "#PR #提供 #タイアップ",
          "position": "closing",
          "reality": "法令遵守のための最低限の表記。目立たない場所に置きがち",
          "example": "#PR #提供 #タイアップ投稿 @brand_official",
          "intensity": 2,
          "tags": [
            "PR",
            "ステマ規制"
          ]
        },
        {
          "text": "リピ確定",
          "position": "closing",
          "reality": "無料提供品を自腹でリピートするかは不明",
          "example": "もうリピ確定！これなしでは生きていけない",
          "intensity": 4,
          "tags": [
            "PR",
            "リピート演出"
          ]
        },
        {
          "text": "忖度なしのレビュー",
          "position": "opening",
          "reality": "「忖度なし」と宣言すること自体が忖度の証拠",
          "example": "忖度なしのガチレビューです。正直に言うと...最高でした",
          "intensity": 4,
          "tags": [
            "PR",
            "信頼性演出"
          ]
        },
        {
          "text": "ずっと使いたかった",
          "position": "opening",
          "reality": "PR案件が来るまで知らなかった可能性大",
          "example": "ずっと使いたかった○○！念願叶ってお試しできました",
          "intensity": 3,
          "tags": [
            "PR",
            "ファン演出"
          ]
        }
      ]
    },
    {
      "id": "other",
      "name": "その他Instagram固有パターン",
      "description": "上記カテゴリに収まらないInstagram特有の構文やパターン。加工・フィルター文化、位置情報マウント、コメント欄の定型返信など。",
      "phrases": [
        {
          "text": "加工じゃないよ",
          "position": "middle",
          "reality": "加工だよ。フィルターと補正を重ねた上での「加工じゃない」宣言",
          "example": "この空の色、加工じゃないよ！肉眼で見たまま",
          "intensity": 3,
          "tags": [
            "加工",
            "嘘"
          ]
        },
        {
          "text": "映え狙いじゃないけど",
          "position": "opening",
          "reality": "映え狙いの写真に「映え狙いじゃない」と言い訳する矛盾",
          "example": "映え狙いじゃないけど、たまたま綺麗に撮れた",
          "intensity": 3,
          "tags": [
            "映え",
            "言い訳"
          ]
        },
        {
          "text": "投稿迷ったけど",
          "position": "opening",
          "reality": "迷っていないし、最初から投稿するつもりの計算された前置き",
          "example": "投稿迷ったけど...記録用に残しておく",
          "intensity": 3,
          "tags": [
            "前置き",
            "予防線"
          ]
        },
        {
          "text": "記録用",
          "position": "closing",
          "reality": "自己満足アピールを「記録」という名目で正当化",
          "example": "#記録用 #自分用メモ (完璧に構図を計算された写真)",
          "intensity": 3,
          "tags": [
            "言い訳",
            "承認欲求"
          ]
        },
        {
          "text": "聞かれることが多いので",
          "position": "opening",
          "reality": "誰も聞いていない。自分から発信したい情報への導入",
          "example": "よく聞かれるので！愛用コスメまとめました",
          "intensity": 4,
          "tags": [
            "自意識",
            "需要捏造"
          ]
        },
        {
          "text": "投稿見てくれてありがとう",
          "position": "closing",
          "reality": "全投稿末尾に付けるテンプレ感謝。機械的で心がこもっていない",
          "example": "最後まで読んでくれてありがとう！いいね・保存してくれると嬉しいです",
          "intensity": 2,
          "tags": [
            "テンプレ",
            "感謝"
          ]
        },
        {
          "text": "今の私があるのは○○のおかげ",
          "position": "closing",
          "reality": "特定のサービス・人物への宣伝を「感謝」で包装",
          "example": "今の私があるのはこのスクールのおかげ。本当に出会えてよかった",
          "intensity": 4,
          "tags": [
            "宣伝",
            "感謝風広告"
          ]
        },
        {
          "text": "○○すぎて語彙力失う",
          "position": "middle",
          "reality": "語彙力は最初からない。思考停止ワード",
          "example": "美味しすぎて語彙力失った...天才かよ",
          "intensity": 3,
          "tags": [
            "語彙力",
            "思考停止"
          ]
        },
        {
          "text": "全人類に届け",
          "position": "closing",
          "reality": "「全人類」に届ける内容ではない。大袈裟な表現の典型",
          "example": "このスキンケア全人類に届け...！",
          "intensity": 3,
          "tags": [
            "誇大",
            "推し"
          ]
        },
        {
          "text": "概念○○",
          "position": "opening",
          "reality": "「概念」の誤用。単に「○○っぽい」と言えばいいだけ",
          "example": "概念カフェに行ってきた。世界観がすごい",
          "intensity": 2,
          "tags": [
            "流行語",
            "誤用"
          ]
        }
      ]
    }
  ],
  "meta": {
    "total_phrases": 100,
    "last_updated": "2026-03-04",
    "sources": [
      "https://note.com/cha_noma11/n/ne95475f9df4b",
      "https://cancam.jp/archives/666404",
      "https://snaplace.biz/instaiya/",
      "https://happymail.co.jp/happylife/special-feature/instagram-girls-features/",
      "https://rocketnews24.com/2017/02/12/859492/",
      "https://muulif.com/hashtag/",
      "https://blog.tinect.jp/?p=77821",
      "https://blog.tinect.jp/?p=77504",
      "https://anny.gift/mag/renai/",
      "https://oggi.jp/6371146",
      "https://cancam.jp/archives/658644"
    ]
  }
}